nonebot_plugin_autoreply-0.2.13.dist-info/METADATA
nonebot_plugin_autoreply-0.2.13.dist-info/WHEEL
nonebot_plugin_autoreply-0.2.13.dist-info/entry_points.txt
nonebot_plugin_autoreply-0.2.13.dist-info/licenses/LICENSE
nonebot_plugin_autoreply/__init__.py
nonebot_plugin_autoreply/__main__.py
nonebot_plugin_autoreply/config.py
nonebot_plugin_autoreply/cool_down.py
nonebot_plugin_autoreply/util.py
nonebot_plugin_autoreply-0.2.13.dist-info/RECORD
