Metadata-Version: 2.1
Name: nonebot-plugin-autoreply
Version: 0.2.13
Summary: A powerful auto reply plugin for NoneBot2
Author-Email: student_2333 <lgc2333@126.com>
License: MIT
Project-URL: homepage, https://github.com/lgc-NB2Dev/nonebot-plugin-autoreply
Requires-Python: <4.0,>=3.9
Requires-Dist: nonebot2>=2.3.1
Requires-Dist: nonebot-adapter-onebot>=2.4.3
Requires-Dist: typing-extensions>=4.12.2
Requires-Dist: PyYAML>=6.0.1
Requires-Dist: anyio>=4.4.0
